Lab1/blackbox.v
module blackbox(n, f, x, e);
    output n;
    input  f, x, e;
    wire   w03, w04, w05, w12, w14, w24, w25, w44, w45, w52, w67, w75, w82, w85;
    or  o13(n, w67, w14, w05);
    and a35(w14, w03, w85);
    not n55(w85, w03);
    and a86(w05, w45, w82);
    not n1(w45, w82);
    or  o87(w82, f, e, x);
    and a64(w03, w52, w04);
    not n31(w52, f);
    or  o26(w04, e, w12);
    and a80(w12, w25, w44);
    not n54(w25, x);
    not n56(w44, e);
    or  o16(w67, w75, f, w24);
    not n43(w75, e);
    not n92(w24, x);
endmodule // blackbox

Lab1/blackbox_tb.v
module blackbox_test;

	reg f, x, e;
	
	wire n;

	blackbox bb (n, f, x ,e);

	initial begin

		$dumpfile("blackbox.vcd");
		$dumpvars(0, blackbox_test);

		f = 0; x = 0; e = 0; #10;
		f = 0; x = 0; e = 1; #10;
		f = 0; x = 1; e = 1; #10;
		f = 1; x = 1; e = 1; #10;
		f = 1; x = 1; e = 0; #10;
		f = 1; x = 0; e = 0; #10;
		f = 1; x = 0; e = 1; #10;
		f = 0; x = 1; e = 0; #10;

		$finish;
	end

	initial
		$monitor("At time %2t, f = %d x = %d e = %d n = %d"
, $time, f, x, e, n);
endmodule // blackbox_test

Lab1/blackbox.vcd
$date
	Mon Aug 28 13:44:06 2017
$end
$version
	Icarus Verilog
$end
$timescale
	1s
$end
$scope module blackbox_test $end
$var wire 1 ! n $end
$var reg 1 " e $end
$var reg 1 # f $end
$var reg 1 $ x $end
$scope module bb $end
$var wire 1 % e $end
$var wire 1 & f $end
$var wire 1 ! n $end
$var wire 1 ' w03 $end
$var wire 1 ( w04 $end
$var wire 1 ) w05 $end
$var wire 1 * w12 $end
$var wire 1 + w14 $end
$var wire 1 , w24 $end
$var wire 1 - w25 $end
$var wire 1 . w44 $end
$var wire 1 / w45 $end
$var wire 1 0 w52 $end
$var wire 1 1 w67 $end
$var wire 1 2 w75 $end
$var wire 1 3 w82 $end
$var wire 1 4 w85 $end
$var wire 1 5 x $end
$upscope $end
$upscope $end
$enddefinitions $end
#0
$dumpvars
05
04
03
12
11
10
1/
1.
1-
1,
0+
1*
0)
1(
1'
0&
0%
0$
0#
0"
1!
$end
#10
0/
0)
0*
13
0.
02
1"
1%
#20
0!
01
0-
0,
1$
15
#30
14
0'
1!
00
11
1#
1&
#40
0(
1.
12
0"
0%
#50
1(
1*
1-
1,
0$
05
#60
0*
0.
02
1"
1%
#70
0(
1.
12
0-
0,
10
0"
0%
1$
15
0#
0&
