Lab3/mux.v
// output = A (when control == 0) or B (when control == 1)
module mux2(out, A, B, control);
    output out;
    input  A, B;
    input  control;
    wire   wA, wB, not_control;
         
    not n1(not_control, control);
    and a1(wA, A, not_control);
    and a2(wB, B, control);
    or  o1(out, wA, wB);
endmodule // mux2

// output = A (when control == 00) or B (when control == 01) or
//          C (when control == 10) or D (when control == 11)
module mux4(out, A, B, C, D, control);
    output      out;
    input       A, B, C, D;
    input [1:0] control;
	wire w1, w2;

	mux2 m1(w1, A, B, control[0]);
	mux2 m2(w2, C, D, control[0]);
	mux2 m3(out, w1, w2, control[1]);

endmodule // mux4

Lab3/logicunit.v
// 00 - AND, 01 - OR, 10 - NOR, 11 - XOR
module logicunit(out, A, B, control);
    output      out;
    input       A, B;
    input [1:0] control;
	wire w1, w2, w3, w4;

	and a1(w1, A, B);
	or o1(w2, A, B);
	nor no1(w3, A, B);
	xor x1(w4, A, B);

	mux4 m1(out, w1, w2, w3, w4, control);

endmodule // logicunit

Lab3/alu1.v
module full_adder(sum, cout, a, b, cin);
    output sum, cout;
    input  a, b, cin;
    wire   partial_s, partial_c1, partial_c2;

    xor x0(partial_s, a, b);
    xor x1(sum, partial_s, cin);
    and a0(partial_c1, a, b);
    and a1(partial_c2, partial_s, cin);
    or  o1(cout, partial_c1, partial_c2);
endmodule // full_adder

`define ALU_ADD    3'h2
`define ALU_SUB    3'h3
`define ALU_AND    3'h4
`define ALU_OR     3'h5
`define ALU_NOR    3'h6
`define ALU_XOR    3'h7

// 01x - arithmetic, 1xx - logic
module alu1(out, carryout, A, B, carryin, control);
    output      out, carryout;
    input       A, B, carryin;
    input [2:0] control;
	wire 		faSum, xorB, luOut;

	xor addorSub(xorB, B, control[0]);
    full_adder fa(faSum, carryout, A, B, carryin);

	logicunit lu(luOut, A, B, control[1:0]);

	mux2 mux(out, faSum, luOut, control[2]);
   
endmodule // alu1

Lab3/alu1_tb.v
module alu1_test;
    reg A, B, carryin;
     
    reg [2:0] control;

    initial begin

        $dumpfile("alu1.vcd");
        $dumpvars(0, alu1_test);

		control[1] = 1;
		control[2] = 0;
		carryin = 0;

		control[0] = 0;
        //tests for addition
        A = 0; B = 0; #10;
		A = 1; B = 0; #10;
		A = 0; B = 1; #10;
		A = 1; B = 1; #10;

		control[0] = 1;
		//tests for subtraction
		A = 0; B = 0; #10;
		A = 1; B = 0; #10;
		A = 0; B = 1; #10;
		A = 1; B = 1; #10;

		control [2] = 1; control [0] = 0; control[1] = 0;
		//tests for and
		A = 0; B = 0; #10;
		A = 1; B = 0; #10;
		A = 0; B = 1; #10;
		A = 1; B = 1; #10;

		control[0] = 1;
		//tests for or
		A = 0; B = 0; #10;
		A = 1; B = 0; #10;
		A = 0; B = 1; #10;
		A = 1; B = 1; #10;

		control[0] = 0; control [1] = 1;
		//tests for nor
		A = 0; B = 0; #10;
		A = 1; B = 0; #10;
		A = 0; B = 1; #10;
		A = 1; B = 1; #10;

		control [0] = 1;
		//test for xor
		A = 0; B = 0; #10;
		A = 1; B = 0; #10;
		A = 0; B = 1; #10;
		A = 1; B = 1; #10;

		$finish;
    end

	wire out, carryout;

	alu1 alu(out, carryout, A, B, carryin, control);

	initial begin
        $display("A B c o cout cin");
        $monitor("%d %d %d %d %d    %d   (at time %t)", A, B, control, out, carryout, carryin, $time);
    end

endmodule

Lab3/alu1.vcd
$date
	Sat Sep 16 18:20:57 2017
$end
$version
	Icarus Verilog
$end
$timescale
	1s
$end
$scope module alu1_test $end
$var wire 1 ! carryout $end
$var wire 1 " out $end
$var reg 1 # A $end
$var reg 1 $ B $end
$var reg 1 % carryin $end
$var reg 3 & control [2:0] $end
$scope module alu $end
$var wire 1 ' A $end
$var wire 1 ( B $end
$var wire 1 ) carryin $end
$var wire 1 ! carryout $end
$var wire 3 * control [2:0] $end
$var wire 1 + faSum $end
$var wire 1 , luOut $end
$var wire 1 " out $end
$var wire 1 - xorB $end
$scope module fa $end
$var wire 1 ' a $end
$var wire 1 ( b $end
$var wire 1 ) cin $end
$var wire 1 ! cout $end
$var wire 1 . partial_c1 $end
$var wire 1 / partial_c2 $end
$var wire 1 0 partial_s $end
$var wire 1 + sum $end
$upscope $end
$scope module lu $end
$var wire 1 ' A $end
$var wire 1 ( B $end
$var wire 2 1 control [1:0] $end
$var wire 1 , out $end
$var wire 1 2 w1 $end
$var wire 1 3 w2 $end
$var wire 1 4 w3 $end
$var wire 1 5 w4 $end
$scope module m1 $end
$var wire 1 2 A $end
$var wire 1 3 B $end
$var wire 1 4 C $end
$var wire 1 5 D $end
$var wire 2 6 control [1:0] $end
$var wire 1 , out $end
$var wire 1 7 w1 $end
$var wire 1 8 w2 $end
$scope module m1 $end
$var wire 1 2 A $end
$var wire 1 3 B $end
$var wire 1 9 control $end
$var wire 1 : not_control $end
$var wire 1 7 out $end
$var wire 1 ; wA $end
$var wire 1 < wB $end
$upscope $end
$scope module m2 $end
$var wire 1 4 A $end
$var wire 1 5 B $end
$var wire 1 = control $end
$var wire 1 > not_control $end
$var wire 1 8 out $end
$var wire 1 ? wA $end
$var wire 1 @ wB $end
$upscope $end
$scope module m3 $end
$var wire 1 7 A $end
$var wire 1 8 B $end
$var wire 1 A control $end
$var wire 1 B not_control $end
$var wire 1 , out $end
$var wire 1 C wA $end
$var wire 1 D wB $end
$upscope $end
$upscope $end
$upscope $end
$scope module mux $end
$var wire 1 + A $end
$var wire 1 , B $end
$var wire 1 E control $end
$var wire 1 F not_control $end
$var wire 1 " out $end
$var wire 1 G wA $end
$var wire 1 H wB $end
$upscope $end
$upscope $end
$upscope $end
$enddefinitions $end
#0
$dumpvars
0H
0G
1F
0E
1D
0C
0B
1A
0@
1?
1>
0=
0<
0;
1:
09
18
07
b10 6
05
14
03
02
b10 1
00
0/
0.
0-
1,
0+
b10 *
0)
0(
0'
b10 &
0%
0$
0#
0"
0!
$end
#10
0,
1"
0D
1G
08
1+
0?
10
13
04
15
1#
1'
#20
1-
1$
1(
0#
0'
#30
0"
0G
17
0+
1!
1;
00
1.
12
05
1#
1'
#40
0,
0D
07
08
0:
0>
0!
0;
0?
19
1=
0.
02
03
14
b11 1
b11 6
0$
0(
0#
0'
b11 &
b11 *
#50
1,
1"
1D
1G
17
18
1+
1<
1@
10
13
04
15
1#
1'
#60
0-
1$
1(
0#
0'
#70
0,
0"
0D
0G
08
0+
1!
0@
00
1.
12
05
1#
1'
#80
18
1?
07
1:
1>
1B
0!
0<
09
0=
0A
0F
0.
02
03
14
b0 1
b0 6
1E
0$
0(
0#
0'
b100 &
b100 *
#90
08
1+
0?
10
13
04
15
1#
1'
#100
1-
1$
1(
0#
0'
#110
1"
1H
1,
1C
17
0+
1!
1;
00
1.
12
05
1#
1'
#120
0"
0H
0,
0C
07
08
0:
0>
0!
0;
0?
19
1=
0.
02
03
14
b1 1
b1 6
0$
0(
0#
0'
b101 &
b101 *
#130
1"
1H
1,
1C
17
18
1+
1<
1@
10
13
04
15
1#
1'
#140
0-
1$
1(
0#
0'
#150
08
0+
1!
0@
00
1.
12
05
1#
1'
#160
1"
1D
1H
18
1,
1?
0C
07
1:
1>
0B
0!
0<
09
0=
1A
0.
02
03
14
b10 1
b10 6
0$
0(
0#
0'
b110 &
b110 *
#170
0"
0H
0,
0D
08
1+
0?
10
13
04
15
1#
1'
#180
1-
1$
1(
0#
0'
#190
17
0+
1!
1;
00
1.
12
05
1#
1'
#200
0"
0H
0,
0D
07
08
0:
0>
0!
0;
0?
19
1=
0.
02
03
14
b11 1
b11 6
0$
0(
0#
0'
b111 &
b111 *
#210
1"
1H
1,
1D
17
18
1+
1<
1@
10
13
04
15
1#
1'
#220
0-
1$
1(
0#
0'
#230
0"
0H
0,
0D
08
0+
1!
0@
00
1.
12
05
1#
1'
