Lab3/mux.v
// output = A (when control == 0) or B (when control == 1)
module mux2(out, A, B, control);
    output out;
    input  A, B;
    input  control;
    wire   wA, wB, not_control;
         
    not n1(not_control, control);
    and a1(wA, A, not_control);
    and a2(wB, B, control);
    or  o1(out, wA, wB);
endmodule // mux2

// output = A (when control == 00) or B (when control == 01) or
//          C (when control == 10) or D (when control == 11)
module mux4(out, A, B, C, D, control);
    output      out;
    input       A, B, C, D;
    input [1:0] control;
	wire w1, w2;

	mux2 m1(w1, A, B, control[0]);
	mux2 m2(w2, C, D, control[0]);
	mux2 m3(out, w1, w2, control[1]);

endmodule // mux4

Lab3/logicunit.v
// 00 - AND, 01 - OR, 10 - NOR, 11 - XOR
module logicunit(out, A, B, control);
    output      out;
    input       A, B;
    input [1:0] control;
	wire w1, w2, w3, w4;

	and a1(w1, A, B);
	or o1(w2, A, B);
	nor no1(w3, A, B);
	xor x1(w4, A, B);

	mux4 m1(out, w1, w2, w3, w4, control);

endmodule // logicunit

Lab3/logicunit_tb.v
module logicunit_test;

    reg A, B;
     
    reg [1:0] control;

    initial begin

        $dumpfile("logicunit.vcd");
        $dumpvars(0, logicunit_test);

		//tests in order of AND, NOR, OR, XOR
        //tests for A and B = 0
        A = 0; B = 0; control[0] = 0; control[1] = 0; #10;
		A = 0; B = 0; control[0] = 0; control[1] = 1; #10;
		A = 0; B = 0; control[0] = 1; control[1] = 0; #10;
		A = 0; B = 0; control[0] = 1; control[1] = 1; #10;
		//tests for A and B = 1
		A = 1; B = 1; control[0] = 0; control[1] = 0; #10;
		A = 1; B = 1; control[0] = 0; control[1] = 1; #10;
		A = 1; B = 1; control[0] = 1; control[1] = 0; #10;
		A = 1; B = 1; control[0] = 1; control[1] = 1; #10;
		//tests for A = 1, B = 0
		A = 1; B = 0; control[0] = 0; control[1] = 0; #10;
		A = 1; B = 0; control[0] = 0; control[1] = 1; #10;
		A = 1; B = 0; control[0] = 1; control[1] = 0; #10;
		A = 1; B = 0; control[0] = 1; control[1] = 1; #10;
		//tests for A = 0, B = 1
		A = 0; B = 1; control[0] = 0; control[1] = 0; #10;
		A = 0; B = 1; control[0] = 0; control[1] = 1; #10;
		A = 0; B = 1; control[0] = 1; control[1] = 0; #10;
		A = 0; B = 1; control[0] = 1; control[1] = 1; #10;

		$finish;
    end

	wire out;
	
	logicunit lu(out, A, B, control);

	initial begin
        $display("A B c o");
        $monitor("%d %d %d %d (at time %t)", A, B, control, out, $time);
    end
	

    
endmodule // logicunit_test

Lab3/logicunit.vcd
$date
	Sat Sep 16 18:20:57 2017
$end
$version
	Icarus Verilog
$end
$timescale
	1s
$end
$scope module logicunit_test $end
$var wire 1 ! out $end
$var reg 1 " A $end
$var reg 1 # B $end
$var reg 2 $ control [1:0] $end
$scope module lu $end
$var wire 1 % A $end
$var wire 1 & B $end
$var wire 2 ' control [1:0] $end
$var wire 1 ! out $end
$var wire 1 ( w1 $end
$var wire 1 ) w2 $end
$var wire 1 * w3 $end
$var wire 1 + w4 $end
$scope module m1 $end
$var wire 1 ( A $end
$var wire 1 ) B $end
$var wire 1 * C $end
$var wire 1 + D $end
$var wire 2 , control [1:0] $end
$var wire 1 ! out $end
$var wire 1 - w1 $end
$var wire 1 . w2 $end
$scope module m1 $end
$var wire 1 ( A $end
$var wire 1 ) B $end
$var wire 1 / control $end
$var wire 1 0 not_control $end
$var wire 1 - out $end
$var wire 1 1 wA $end
$var wire 1 2 wB $end
$upscope $end
$scope module m2 $end
$var wire 1 * A $end
$var wire 1 + B $end
$var wire 1 3 control $end
$var wire 1 4 not_control $end
$var wire 1 . out $end
$var wire 1 5 wA $end
$var wire 1 6 wB $end
$upscope $end
$scope module m3 $end
$var wire 1 - A $end
$var wire 1 . B $end
$var wire 1 7 control $end
$var wire 1 8 not_control $end
$var wire 1 ! out $end
$var wire 1 9 wA $end
$var wire 1 : wB $end
$upscope $end
$upscope $end
$upscope $end
$upscope $end
$enddefinitions $end
#0
$dumpvars
0:
09
18
07
06
15
14
03
02
01
10
0/
1.
0-
b0 ,
0+
1*
0)
0(
b0 '
0&
0%
b0 $
0#
0"
0!
$end
#10
1!
08
1:
17
b10 '
b10 ,
b10 $
#20
0.
0!
05
18
0:
00
04
07
1/
13
b1 $
b1 '
b1 ,
#30
08
17
b11 '
b11 ,
b11 $
#40
1!
19
1-
11
18
10
14
07
0/
03
1(
1)
0*
b0 $
b0 '
b0 ,
1#
1&
1"
1%
#50
0!
09
08
17
b10 '
b10 ,
b10 $
#60
1!
19
01
18
00
12
04
07
1/
13
b1 $
b1 '
b1 ,
#70
0!
09
08
17
b11 '
b11 ,
b11 $
#80
0-
18
10
02
14
07
0/
03
0(
1+
b0 $
b0 '
b0 ,
0#
0&
#90
08
17
b10 '
b10 ,
b10 $
#100
1!
19
1-
1.
18
00
12
04
16
07
1/
13
b1 $
b1 '
b1 ,
#110
09
08
1:
17
b11 '
b11 ,
b11 $
#120
0!
0-
0.
18
0:
10
02
14
06
07
0/
03
b0 $
b0 '
b0 ,
1#
1&
0"
0%
#130
08
17
b10 '
b10 ,
b10 $
#140
1!
19
1-
1.
18
00
12
04
16
07
1/
13
b1 $
b1 '
b1 ,
#150
09
08
1:
17
b11 '
b11 ,
b11 $
